cfb-0.8.3.dist-info/METADATA
cfb-0.8.3.dist-info/WHEEL
cfb-0.8.3.dist-info/RECORD
cfb-0.8.3.dist-info/DESCRIPTION.rst
cfb-0.8.3.dist-info/top_level.txt
cfb-0.8.3.dist-info/pydist.json
tests/test_entry.py
tests/__init__.py
tests/test_header.py
tests/test_directory.py
tests/test_helpers.py
tests/test_exceptions.py
tests/data/simple.doc
cfb/__init__.py
cfb/helpers.py
cfb/header.py
cfb/exceptions.py
cfb/constants.py
cfb/directory/__init__.py
cfb/directory/entry.py
