Metadata-Version: 1.1
Name: cfb
Version: 0.8.3
Summary: Microsoft Compound File Binary File Format IO
Home-page: https://github.com/rembish/cfb
Author: Alex Rembish
Author-email: alex@rembish.org
License: BSD 2-Clause license
Platform: UNKNOWN
Classifier: Development Status :: 3 - Alpha
Classifier: Intended Audience :: Developers
Classifier: License :: OSI Approved :: BSD License
Classifier: Programming Language :: Python
Classifier: Programming Language :: Python :: 2.6
Classifier: Programming Language :: Python :: 2.7
Classifier: Programming Language :: Python :: 3.2
Classifier: Programming Language :: Python :: 3.3
Classifier: Topic :: Software Development :: Libraries
Classifier: Topic :: Software Development :: Libraries :: Python Modules
Classifier: Topic :: Text Processing
